bytedance_custom_rate_limiter/__init__.py
bytedance_custom_rate_limiter-0.0.1.dist-info/METADATA
bytedance_custom_rate_limiter-0.0.1.dist-info/WHEEL
bytedance_custom_rate_limiter-0.0.1.dist-info/top_level.txt
bytedance_custom_rate_limiter-0.0.1.dist-info/RECORD
